[{"id":"444baae6b6ddc0b7","type":"inject","z":"fbee74db83781e91","name":"Inject host & port","props":[{"p":"payload"},{"p":"topic","vt":"str"}],"repeat":"","crontab":"","once":false,"onceDelay":0.1,"topic":"","payload":"{\"host\":\"localhost\",\"port\":1880}","payloadType":"json","x":600,"y":1620,"wires":[["b585a098132c8d9b"]]},{"id":"b585a098132c8d9b","type":"certificate-grabber","z":"fbee74db83781e91","name":"","host":"payload.host","hostType":"msg","port":"payload.port","portType":"msg","timeout":"10","x":810,"y":1620,"wires":[["28d9f5baa0619f96"]]},{"id":"28d9f5baa0619f96","type":"switch","z":"fbee74db83781e91","name":"daysRemaining","property":"payload.daysRemaining","propertyType":"msg","rules":[{"t":"btwn","v":"1","vt":"num","v2":"5","v2t":"num"},{"t":"lte","v":"0","vt":"num"}],"checkall":"true","repair":false,"outputs":2,"x":1020,"y":1620,"wires":[["7a4aefe0bdd4beac"],["ebfdce39f8c15bb7"]],"outputLabels":["going to expire","expired"]},{"id":"7a4aefe0bdd4beac","type":"debug","z":"fbee74db83781e91","name":"Warning","active":true,"tosidebar":true,"console":false,"tostatus":false,"complete":"payload","targetType":"msg","statusVal":"","statusType":"auto","x":1220,"y":1600,"wires":[]},{"id":"ebfdce39f8c15bb7","type":"debug","z":"fbee74db83781e91","name":"Problem","active":true,"tosidebar":true,"console":false,"tostatus":false,"complete":"payload","targetType":"msg","statusVal":"","statusType":"auto","x":1220,"y":1640,"wires":[]}]
